<Entity name="BossCrystal" maxAlive="50">
	<GravityFlip>False</GravityFlip>
	<Collision Enabled="False">
		<Hitbox name="H" x="-4" y="-4" width="8" height="8" properties="Default" damage="3" environment="True" pushaway="True">
			<Hits>Player</Hits>
			<Group>Projectile</Group>
			<Group>Solid</Group>
		</Hitbox>
	</Collision>
	<Health max="1" flash="0" />
	<Sprite width="8" height="8" tilesheet="images\weapons\crystal.png">
		<Hotspot x="4" y="4" />
		<Frame x="80" y="0" duration="8" />
		<Frame x="88" y="0" duration="8" />
		<Frame x="96" y="0" duration="8" />
		<Frame x="104" y="0" duration="8" />
		<Frame x="112" y="0" duration="8" />
	</Sprite>
	<State name="Start">
		<Initialize>
			<Collision>
				<EnableBox name="H" />
			</Collision>
			<Position>
				<X base="Inherit" />
				<Y base="Inherit" />
			</Position>
			<Flying>True</Flying>
			<FlipSprite />
		</Initialize>
		<Logic />
	</State>
	<State name="UpLeft">
		<Initialize />
		<Logic>
			<Flying />
			<FlipSprite />
			<X direction="Left" magnitude="2.8" />
			<Y direction="Up" magnitude="2.8" />
		</Logic>
		<Trigger>
			<Condition>Collision.BlockLeft == True</Condition>
			<Effect>
				<State>UpRight</State>
			</Effect>
		</Trigger>
		<Trigger>
			<Condition>Collision.BlockTop == True</Condition>
			<Effect>
				<State>DownLeft</State>
			</Effect>
		</Trigger>
		<Trigger>
			<Condition>LifeTime &gt; 300</Condition>
			<Effect>
				<Remove />
			</Effect>
		</Trigger>
	</State>
	<State name="UpRight">
		<Initialize />
		<Logic>
			<Flying />
			<FlipSprite />
			<X direction="Right" magnitude="2.8" />
			<Y direction="Up" magnitude="2.8" />
		</Logic>
		<Trigger>
			<Condition>Collision.BlockRight == True</Condition>
			<Effect>
				<State>UpLeft</State>
			</Effect>
		</Trigger>
		<Trigger>
			<Condition>Collision.BlockTop == True</Condition>
			<Effect>
				<State>DownRight</State>
			</Effect>
		</Trigger>
		<Trigger>
			<Condition>LifeTime &gt; 300</Condition>
			<Effect>
				<Remove />
			</Effect>
		</Trigger>
	</State>
	<State name="DownLeft">
		<Initialize />
		<Logic>
			<Flying />
			<FlipSprite />
			<X direction="Left" magnitude="2.8" />
			<Y direction="Down" magnitude="2.8" />
		</Logic>
		<Trigger>
			<Condition>Collision.BlockLeft == True</Condition>
			<Effect>
				<State>DownRight</State>
			</Effect>
		</Trigger>
		<Trigger>
			<Condition>Collision.BlockBottom == True</Condition>
			<Effect>
				<State>UpLeft</State>
			</Effect>
		</Trigger>
		<Trigger>
			<Condition>LifeTime &gt; 300</Condition>
			<Effect>
				<Remove />
			</Effect>
		</Trigger>
	</State>
	<State name="DownRight">
		<Initialize />
		<Logic>
			<Flying />
			<FlipSprite />
			<X direction="Right" magnitude="2.8" />
			<Y direction="Down" magnitude="2.8" />
		</Logic>
		<Trigger>
			<Condition>Collision.BlockRight == True</Condition>
			<Effect>
				<State>DownLeft</State>
			</Effect>
		</Trigger>
		<Trigger>
			<Condition>Collision.BlockBottom == True</Condition>
			<Effect>
				<State>UpRight</State>
			</Effect>
		</Trigger>
		<Trigger>
			<Condition>LifeTime &gt; 300</Condition>
			<Effect>
				<Remove />
			</Effect>
		</Trigger>
	</State>
	<Trigger>
		<Condition>Collision.DamageDealt &gt; 0</Condition>
		<Effect>
			<Remove />
		</Effect>
	</Trigger>
	<Movement>
		<Flying />
		<FlipSprite />
	</Movement>
</Entity>