<Entity name="Dust" maxAlive="50">
	<GravityFlip>False</GravityFlip>
	<Sprite width="8" height="8" tilesheet="images\particles\dust_-_spark.png">
		<Hotspot x="4" y="-5" />
		<Frame x="0" y="8" duration="1" />
		<Frame x="0" y="0" duration="8" />
		<Frame x="8" y="0" duration="8" />
		<Frame x="16" y="0" duration="1" />
	</Sprite>
	<State name="Start">
		<Initialize>
			<Position>
				<X base="Inherit" />
				<Y base="Inherit" />
			</Position>
			<Flying>True</Flying>
			<FlipSprite />
		</Initialize>
		<Logic />
		<Trigger>
			<Condition>StateTime&gt;=18</Condition>
			<Effect>
				<Die />
			</Effect>
		</Trigger>
	</State>
	<Movement>
		<Flying />
		<FlipSprite />
	</Movement>
</Entity>